MANIFEST.in
setup.py
docs/CONTRIBUTORS.txt
docs/HISTORY.txt
docs/LICENSE.txt
docs/README.txt
src/ztfy/__init__.py
src/ztfy.mail.egg-info/PKG-INFO
src/ztfy.mail.egg-info/SOURCES.txt
src/ztfy.mail.egg-info/dependency_links.txt
src/ztfy.mail.egg-info/namespace_packages.txt
src/ztfy.mail.egg-info/not-zip-safe
src/ztfy.mail.egg-info/requires.txt
src/ztfy.mail.egg-info/top_level.txt
src/ztfy/mail/__init__.py
src/ztfy/mail/adapter.py
src/ztfy/mail/configure.zcml
src/ztfy/mail/interfaces.py
src/ztfy/mail/message.py
src/ztfy/mail/vocabulary.py
src/ztfy/mail/doctests/README.txt
src/ztfy/mail/locales/ztfy.mail.pot
src/ztfy/mail/locales/en/LC_MESSAGES/ztfy.mail.mo
src/ztfy/mail/locales/en/LC_MESSAGES/ztfy.mail.po
src/ztfy/mail/locales/fr/LC_MESSAGES/ztfy.mail.mo
src/ztfy/mail/locales/fr/LC_MESSAGES/ztfy.mail.po
src/ztfy/mail/tests/__init__.py
src/ztfy/mail/tests/test_docs.py
src/ztfy/mail/tests/test_docstrings.py