Metadata-Version: 1.1
Name: ztfy.mail
Version: 0.1.5
Summary: ZTFY interfaces and utilities for mail handling
Home-page: http://www.ztfy.org
Author: Thierry Florac
Author-email: tflorac@ulthar.net
License: ZPL
Platform: UNKNOWN
Classifier: Programming Language :: Python
